[
    {
        "Season": 2022,
        "SeasonType": "REG",
        "Week": 12,
        "EliasID": "AVE456819",
        "GsisID": "00-0034682",
        "JerseyNumber": "59",
        "LastName": "Avery",
        "FootballName": "Genard",
        "FirstName": "Genardveous",
        "Position": "OLB",
        "PositionDescription": "Outside Linebacker",
        "EntryYear": 2018,
        "RookieYear": 2018,
        "Height": "6'00\"",
        "Weight": 250,
        "Birthdate": "1995-04-26T00:00:00",
        "DraftClub": "CLV",
        "DraftNumber": 150,
        "Draftround": 5,
        "CurrentClub": "TB",
        "College": "Memphis",
        "CollegeConference": "American Athletic Conference",
        "StatusDescriptionAbbr": "A01",
        "StatusShortDescription": "Active",
        "Playerid": 46219
    },
    {
        "Season": 2022,
        "SeasonType": "REG",
        "Week": 12,
        "EliasID": "BER219765",
        "GsisID": "00-0030456",
        "JerseyNumber": "25",
        "LastName": "Bernard",
        "FootballName": "Giovani",
        "FirstName": "Giovani",
        "Position": "RB",
        "PositionDescription": "Running Back",
        "EntryYear": 2013,
        "RookieYear": 2013,
        "Height": "5'09\"",
        "Weight": 205,
        "Birthdate": "1991-11-22T00:00:00",
        "DraftClub": "CIN",
        "DraftNumber": 37,
        "Draftround": 2,
        "CurrentClub": "TB",
        "College": "North Carolina",
        "CollegeConference": "Atlantic Coast Conference",
        "StatusDescriptionAbbr": "A01",
        "StatusShortDescription": "Active",
        "Playerid": 39985
    },
    {
        "Season": 2022,
        "SeasonType": "REG",
        "Week": 12,
        "EliasID": "BRA371156",
        "GsisID": "00-0019596",
        "JerseyNumber": "12",
        "LastName": "Brady",
        "FootballName": "Tom",
        "FirstName": "Tom",
        "Position": "QB",
        "PositionDescription": "Quarterback",
        "EntryYear": 2000,
        "RookieYear": 2000,
        "Height": "6'04''",
        "Weight": 225,
        "Birthdate": "1977-08-03T00:00:00",
        "DraftClub": "NE",
        "DraftNumber": 199,
        "Draftround": 6,
        "CurrentClub": "TB",
        "College": "Michigan",
        "CollegeConference": "Big Ten Conference",
        "StatusDescriptionAbbr": "A01",
        "StatusShortDescription": "Active",
        "Playerid": 25511
    },
    {
        "Season": 2022,
        "SeasonType": "REG",
        "Week": 12,
        "EliasID": "BRA663798",
        "GsisID": "00-0031273",
        "JerseyNumber": "84",
        "LastName": "Brate",
        "FootballName": "Cameron",
        "FirstName": "Cameron",
        "Position": "TE",
        "PositionDescription": "Tight End",
        "EntryYear": 2014,
        "RookieYear": 2014,
        "Height": "6'05\"",
        "Weight": 245,
        "Birthdate": "1991-07-03T00:00:00",
        "DraftClub": null,
        "DraftNumber": null,
        "Draftround": null,
        "CurrentClub": "TB",
        "College": "Harvard",
        "CollegeConference": "Ivy League",
        "StatusDescriptionAbbr": "A01",
        "StatusShortDescription": "Active",
        "Playerid": 42033
    },
    {
        "Season": 2022,
        "SeasonType": "REG",
        "Week": 12,
        "EliasID": "CAM013278",
        "GsisID": "00-0038042",
        "JerseyNumber": "5",
        "LastName": "Camarda",
        "FootballName": "Jake",
        "FirstName": "Jake",
        "Position": "P",
        "PositionDescription": "Punter",
        "EntryYear": 2022,
        "RookieYear": 2022,
        "Height": "6'02\"",
        "Weight": 180,
        "Birthdate": "1999-04-20T00:00:00",
        "DraftClub": "TB",
        "DraftNumber": 133,
        "Draftround": 4,
        "CurrentClub": "TB",
        "College": "Georgia",
        "CollegeConference": "Southeastern Conference",
        "StatusDescriptionAbbr": "A01",
        "StatusShortDescription": "Active",
        "Playerid": 54598
    },
    {
        "Season": 2022,
        "SeasonType": "REG",
        "Week": 12,
        "EliasID": "DAR261346",
        "GsisID": "00-0036877",
        "JerseyNumber": "1",
        "LastName": "Darden",
        "FootballName": "Jaelon",
        "FirstName": "Jaelon",
        "Position": "WR",
        "PositionDescription": "Wide Receiver",
        "EntryYear": 2021,
        "RookieYear": 2021,
        "Height": "5'09\"",
        "Weight": 174,
        "Birthdate": "1999-01-14T00:00:00",
        "DraftClub": "TB",
        "DraftNumber": 129,
        "Draftround": 4,
        "CurrentClub": "TB",
        "College": "North Texas",
        "CollegeConference": "Conference USA",
        "StatusDescriptionAbbr": "A01",
        "StatusShortDescription": "Active",
        "Playerid": 53558
    },
    {
        "Season": 2022,
        "SeasonType": "REG",
        "Week": 12,
        "EliasID": "DAV026654",
        "GsisID": "00-0029562",
        "JerseyNumber": "54",
        "LastName": "David",
        "FootballName": "Lavonte",
        "FirstName": "Lavonte",
        "Position": "ILB",
        "PositionDescription": "Inside Linebacker",
        "EntryYear": 2012,
        "RookieYear": 2012,
        "Height": "6'01\"",
        "Weight": 233,
        "Birthdate": "1990-01-23T00:00:00",
        "DraftClub": "TB",
        "DraftNumber": 58,
        "Draftround": 2,
        "CurrentClub": "TB",
        "College": "Nebraska",
        "CollegeConference": "Big Ten Conference",
        "StatusDescriptionAbbr": "A01",
        "StatusShortDescription": "Active",
        "Playerid": 38588
    },
    {
        "Season": 2022,
        "SeasonType": "REG",
        "Week": 12,
        "EliasID": "DAV220184",
        "GsisID": "00-0034778",
        "JerseyNumber": "24",
        "LastName": "Davis",
        "FootballName": "Carlton",
        "FirstName": "Carlton",
        "Position": "CB",
        "PositionDescription": "Cornerback",
        "EntryYear": 2018,
        "RookieYear": 2018,
        "Height": "6'01\"",
        "Weight": 206,
        "Birthdate": "1996-12-31T00:00:00",
        "DraftClub": "TB",
        "DraftNumber": 63,
        "Draftround": 2,
        "CurrentClub": "TB",
        "College": "Auburn",
        "CollegeConference": "Southeastern Conference",
        "StatusDescriptionAbbr": "A01",
        "StatusShortDescription": "Active",
        "Playerid": 46132
    },
    {
        "Season": 2022,
        "SeasonType": "REG",
        "Week": 12,
        "EliasID": "DEA114360",
        "GsisID": "00-0035699",
        "JerseyNumber": "35",
        "LastName": "Dean",
        "FootballName": "Jamel",
        "FirstName": "Jamel",
        "Position": "CB",
        "PositionDescription": "Cornerback",
        "EntryYear": 2019,
        "RookieYear": 2019,
        "Height": "6'01\"",
        "Weight": 206,
        "Birthdate": "1996-10-15T00:00:00",
        "DraftClub": "TB",
        "DraftNumber": 94,
        "Draftround": 3,
        "CurrentClub": "TB",
        "College": "Auburn",
        "CollegeConference": "Southeastern Conference",
        "StatusDescriptionAbbr": "A01",
        "StatusShortDescription": "Active",
        "Playerid": 47877
    },
    {
        "Season": 2022,
        "SeasonType": "REG",
        "Week": 12,
        "EliasID": "DEL081488",
        "GsisID": "00-0034515",
        "JerseyNumber": "30",
        "LastName": "Delaney",
        "FootballName": "Dee",
        "FirstName": "DeVonta'",
        "Position": "CB",
        "PositionDescription": "Cornerback",
        "EntryYear": 2018,
        "RookieYear": 2018,
        "Height": "6'01\"",
        "Weight": 193,
        "Birthdate": "1995-02-20T00:00:00",
        "DraftClub": null,
        "DraftNumber": null,
        "Draftround": null,
        "CurrentClub": "TB",
        "College": "Miami",
        "CollegeConference": "Atlantic Coast Conference",
        "StatusDescriptionAbbr": "A01",
        "StatusShortDescription": "Active",
        "Playerid": 46699
    },
    {
        "Season": 2022,
        "SeasonType": "REG",
        "Week": 12,
        "EliasID": "EDW337482",
        "GsisID": "00-0035681",
        "JerseyNumber": "32",
        "LastName": "Edwards",
        "FootballName": "Mike",
        "FirstName": "Mike",
        "Position": "FS",
        "PositionDescription": "Free Safety",
        "EntryYear": 2019,
        "RookieYear": 2019,
        "Height": "5'10\"",
        "Weight": 200,
        "Birthdate": "1996-05-18T00:00:00",
        "DraftClub": "TB",
        "DraftNumber": 99,
        "Draftround": 3,
        "CurrentClub": "TB",
        "College": "Kentucky",
        "CollegeConference": "Southeastern Conference",
        "StatusDescriptionAbbr": "A01",
        "StatusShortDescription": "Active",
        "Playerid": 47882
    },
    {
        "Season": 2022,
        "SeasonType": "REG",
        "Week": 12,
        "EliasID": "EVA534309",
        "GsisID": "00-0031408",
        "JerseyNumber": "13",
        "LastName": "Evans",
        "FootballName": "Mike",
        "FirstName": "Mike",
        "Position": "WR",
        "PositionDescription": "Wide Receiver",
        "EntryYear": 2014,
        "RookieYear": 2014,
        "Height": "6'05\"",
        "Weight": 231,
        "Birthdate": "1993-08-21T00:00:00",
        "DraftClub": "TB",
        "DraftNumber": 7,
        "Draftround": 1,
        "CurrentClub": "TB",
        "College": "Texas A&amp;M",
        "CollegeConference": "Southeastern Conference",
        "StatusDescriptionAbbr": "A01",
        "StatusShortDescription": "Active",
        "Playerid": 41233
    },
    {
        "Season": 2022,
        "SeasonType": "REG",
        "Week": 12,
        "EliasID": "FAT663851",
        "GsisID": "00-0037481",
        "JerseyNumber": "53",
        "LastName": "Fatukasi",
        "FootballName": "Olakunle",
        "FirstName": "Olakunle",
        "Position": "ILB",
        "PositionDescription": "Inside Linebacker",
        "EntryYear": 2022,
        "RookieYear": 2022,
        "Height": "6'00\"",
        "Weight": 230,
        "Birthdate": "1999-06-11T00:00:00",
        "DraftClub": null,
        "DraftNumber": null,
        "Draftround": null,
        "CurrentClub": "TB",
        "College": "Rutgers",
        "CollegeConference": "Big Ten Conference",
        "StatusDescriptionAbbr": "A01",
        "StatusShortDescription": "Active",
        "Playerid": 55069
    },
    {
        "Season": 2022,
        "SeasonType": "REG",
        "Week": 12,
        "EliasID": "FOU564970",
        "GsisID": "00-0033856",
        "JerseyNumber": "7",
        "LastName": "Fournette",
        "FootballName": "Leonard",
        "FirstName": "Leonard",
        "Position": "RB",
        "PositionDescription": "Running Back",
        "EntryYear": 2017,
        "RookieYear": 2017,
        "Height": "6'00\"",
        "Weight": 228,
        "Birthdate": "1995-01-18T00:00:00",
        "DraftClub": "JAX",
        "DraftNumber": 4,
        "Draftround": 1,
        "CurrentClub": "TB",
        "College": "Louisiana State",
        "CollegeConference": "Southeastern Conference",
        "StatusDescriptionAbbr": "I01",
        "StatusShortDescription": "Inactive",
        "Playerid": 44816
    },
    {
        "Season": 2022,
        "SeasonType": "REG",
        "Week": 12,
        "EliasID": "GAB221145",
        "GsisID": "00-0027948",
        "JerseyNumber": "11",
        "LastName": "Gabbert",
        "FootballName": "Blaine",
        "FirstName": "Blaine",
        "Position": "QB",
        "PositionDescription": "Quarterback",
        "EntryYear": 2011,
        "RookieYear": 2011,
        "Height": "6'04\"",
        "Weight": 235,
        "Birthdate": "1989-10-15T00:00:00",
        "DraftClub": "JAX",
        "DraftNumber": 10,
        "Draftround": 1,
        "CurrentClub": "TB",
        "College": "Missouri",
        "CollegeConference": "Big Twelve Conference",
        "StatusDescriptionAbbr": "A01",
        "StatusShortDescription": "Active",
        "Playerid": 37083
    },
    {
        "Season": 2022,
        "SeasonType": "REG",
        "Week": 12,
        "EliasID": "GAG130654",
        "GsisID": "00-0034411",
        "JerseyNumber": "17",
        "LastName": "Gage",
        "FootballName": "Russell",
        "FirstName": "Russell",
        "Position": "WR",
        "PositionDescription": "Wide Receiver",
        "EntryYear": 2018,
        "RookieYear": 2018,
        "Height": "6'00\"",
        "Weight": 184,
        "Birthdate": "1996-01-22T00:00:00",
        "DraftClub": "ATL",
        "DraftNumber": 194,
        "Draftround": 6,
        "CurrentClub": "TB",
        "College": "Louisiana State",
        "CollegeConference": "Southeastern Conference",
        "StatusDescriptionAbbr": "I01",
        "StatusShortDescription": "Inactive",
        "Playerid": 46263
    },
    {
        "Season": 2022,
        "SeasonType": "REG",
        "Week": 12,
        "EliasID": "GHO405127",
        "GsisID": "00-0030386",
        "JerseyNumber": "92",
        "LastName": "Gholston",
        "FootballName": "William",
        "FirstName": "William",
        "Position": "DE",
        "PositionDescription": "Defensive End",
        "EntryYear": 2013,
        "RookieYear": 2013,
        "Height": "6'06\"",
        "Weight": 281,
        "Birthdate": "1991-07-31T00:00:00",
        "DraftClub": "TB",
        "DraftNumber": 126,
        "Draftround": 4,
        "CurrentClub": "TB",
        "College": "Michigan State",
        "CollegeConference": "Big Ten Conference",
        "StatusDescriptionAbbr": "A01",
        "StatusShortDescription": "Active",
        "Playerid": 40074
    },
    {
        "Season": 2022,
        "SeasonType": "REG",
        "Week": 12,
        "EliasID": "GIL128565",
        "GsisID": "00-0035223",
        "JerseyNumber": "57",
        "LastName": "Gilbert",
        "FootballName": "Ulysees",
        "FirstName": "Ulysees",
        "Position": "ILB",
        "PositionDescription": "Inside Linebacker",
        "EntryYear": 2019,
        "RookieYear": 2019,
        "Height": "6'00\"",
        "Weight": 230,
        "Birthdate": "1997-08-09T00:00:00",
        "DraftClub": "PIT",
        "DraftNumber": 207,
        "Draftround": 6,
        "CurrentClub": "TB",
        "College": "Akron",
        "CollegeConference": "Mid-American Conference",
        "StatusDescriptionAbbr": "A01",
        "StatusShortDescription": "Active",
        "Playerid": 47990
    },
    {
        "Season": 2022,
        "SeasonType": "REG",
        "Week": 12,
        "EliasID": "GOD549393",
        "GsisID": "00-0033921",
        "JerseyNumber": "14",
        "LastName": "Godwin",
        "FootballName": "Chris",
        "FirstName": "Rod",
        "Position": "WR",
        "PositionDescription": "Wide Receiver",
        "EntryYear": 2017,
        "RookieYear": 2017,
        "Height": "6'01\"",
        "Weight": 209,
        "Birthdate": "1996-02-27T00:00:00",
        "DraftClub": "TB",
        "DraftNumber": 84,
        "Draftround": 3,
        "CurrentClub": "TB",
        "College": "Penn State",
        "CollegeConference": "Big Ten Conference",
        "StatusDescriptionAbbr": "A01",
        "StatusShortDescription": "Active",
        "Playerid": 44896
    },
    {
        "Season": 2022,
        "SeasonType": "REG",
        "Week": 12,
        "EliasID": "GOE594395",
        "GsisID": "00-0037835",
        "JerseyNumber": "67",
        "LastName": "Goedeke",
        "FootballName": "Luke",
        "FirstName": "Luke",
        "Position": "G",
        "PositionDescription": "Guard",
        "EntryYear": 2022,
        "RookieYear": 2022,
        "Height": "6'05\"",
        "Weight": 310,
        "Birthdate": "1998-11-21T00:00:00",
        "DraftClub": "TB",
        "DraftNumber": 57,
        "Draftround": 2,
        "CurrentClub": "TB",
        "College": "Central Michigan",
        "CollegeConference": "Mid-American Conference",
        "StatusDescriptionAbbr": "I01",
        "StatusShortDescription": "Inactive",
        "Playerid": 54522
    },
    {
        "Season": 2022,
        "SeasonType": "REG",
        "Week": 12,
        "EliasID": "HAI619935",
        "GsisID": "00-0036985",
        "JerseyNumber": "70",
        "LastName": "Hainsey",
        "FootballName": "Robert",
        "FirstName": "Robert",
        "Position": "C",
        "PositionDescription": "Center",
        "EntryYear": 2021,
        "RookieYear": 2021,
        "Height": "6'05\"",
        "Weight": 295,
        "Birthdate": "1998-08-12T00:00:00",
        "DraftClub": "TB",
        "DraftNumber": 95,
        "Draftround": 3,
        "CurrentClub": "TB",
        "College": "Notre Dame",
        "CollegeConference": "Independent",
        "StatusDescriptionAbbr": "A01",
        "StatusShortDescription": "Active",
        "Playerid": 53524
    },
    {
        "Season": 2022,
        "SeasonType": "REG",
        "Week": 12,
        "EliasID": "HAL437521",
        "GsisID": "00-0038127",
        "JerseyNumber": "90",
        "LastName": "Hall",
        "FootballName": "Logan",
        "FirstName": "Logan",
        "Position": "DE",
        "PositionDescription": "Defensive End",
        "EntryYear": 2022,
        "RookieYear": 2022,
        "Height": "6'06\"",
        "Weight": 275,
        "Birthdate": "2000-04-22T00:00:00",
        "DraftClub": "TB",
        "DraftNumber": 33,
        "Draftround": 2,
        "CurrentClub": "TB",
        "College": "Houston",
        "CollegeConference": "American Athletic Conference",
        "StatusDescriptionAbbr": "A01",
        "StatusShortDescription": "Active",
        "Playerid": 54498
    },
    {
        "Season": 2022,
        "SeasonType": "REG",
        "Week": 12,
        "EliasID": "HIC340209",
        "GsisID": "00-0029657",
        "JerseyNumber": "96",
        "LastName": "Hicks",
        "FootballName": "Akiem",
        "FirstName": "Akiem",
        "Position": "DT",
        "PositionDescription": "Defensive Tackle",
        "EntryYear": 2012,
        "RookieYear": 2012,
        "Height": "6'04\"",
        "Weight": 352,
        "Birthdate": "1989-11-16T00:00:00",
        "DraftClub": "NO",
        "DraftNumber": 89,
        "Draftround": 3,
        "CurrentClub": "TB",
        "College": "Regina, Can.",
        "CollegeConference": "Canada West Universities Athletic Association",
        "StatusDescriptionAbbr": "A01",
        "StatusShortDescription": "Active",
        "Playerid": 38619
    },
    {
        "Season": 2022,
        "SeasonType": "REG",
        "Week": 12,
        "EliasID": "JON640315",
        "GsisID": "00-0027944",
        "JerseyNumber": "6",
        "LastName": "Jones",
        "FootballName": "Julio",
        "FirstName": "Quintorris",
        "Position": "WR",
        "PositionDescription": "Wide Receiver",
        "EntryYear": 2011,
        "RookieYear": 2011,
        "Height": "6'03\"",
        "Weight": 220,
        "Birthdate": "1989-02-08T00:00:00",
        "DraftClub": "ATL",
        "DraftNumber": 6,
        "Draftround": 1,
        "CurrentClub": "TB",
        "College": "Alabama",
        "CollegeConference": "Southeastern Conference",
        "StatusDescriptionAbbr": "A01",
        "StatusShortDescription": "Active",
        "Playerid": 37079
    },
    {
        "Season": 2022,
        "SeasonType": "REG",
        "Week": 12,
        "EliasID": "KIE106484",
        "GsisID": "00-0037311",
        "JerseyNumber": "41",
        "LastName": "Kieft",
        "FootballName": "Ko",
        "FirstName": "Ko",
        "Position": "TE",
        "PositionDescription": "Tight End",
        "EntryYear": 2022,
        "RookieYear": 2022,
        "Height": "6'05\"",
        "Weight": 265,
        "Birthdate": "1998-01-20T00:00:00",
        "DraftClub": "TB",
        "DraftNumber": 218,
        "Draftround": 6,
        "CurrentClub": "TB",
        "College": "Minnesota",
        "CollegeConference": "Big Ten Conference",
        "StatusDescriptionAbbr": "A01",
        "StatusShortDescription": "Active",
        "Playerid": 54683
    },
    {
        "Season": 2022,
        "SeasonType": "REG",
        "Week": 12,
        "EliasID": "LEV452663",
        "GsisID": "00-0036105",
        "JerseyNumber": "60",
        "LastName": "Leverett",
        "FootballName": "Nick",
        "FirstName": "Nick",
        "Position": "G",
        "PositionDescription": "Guard",
        "EntryYear": 2020,
        "RookieYear": 2020,
        "Height": "6'04\"",
        "Weight": 310,
        "Birthdate": "1997-01-11T00:00:00",
        "DraftClub": null,
        "DraftNumber": null,
        "Draftround": null,
        "CurrentClub": "TB",
        "College": "Rice",
        "CollegeConference": "Conference USA",
        "StatusDescriptionAbbr": "A01",
        "StatusShortDescription": "Active",
        "Playerid": 53009
    },
    {
        "Season": 2022,
        "SeasonType": "REG",
        "Week": 12,
        "EliasID": "MAS237768",
        "GsisID": "00-0031580",
        "JerseyNumber": "69",
        "LastName": "Mason",
        "FootballName": "Shaquille",
        "FirstName": "Shaquille",
        "Position": "G",
        "PositionDescription": "Guard",
        "EntryYear": 2015,
        "RookieYear": 2015,
        "Height": "6'01\"",
        "Weight": 310,
        "Birthdate": "1993-08-28T00:00:00",
        "DraftClub": "NE",
        "DraftNumber": 131,
        "Draftround": 4,
        "CurrentClub": "TB",
        "College": "Georgia Tech",
        "CollegeConference": "Atlantic Coast Conference",
        "StatusDescriptionAbbr": "A01",
        "StatusShortDescription": "Active",
        "Playerid": 42474
    },
    {
        "Season": 2022,
        "SeasonType": "REG",
        "Week": 12,
        "EliasID": "MCC496223",
        "GsisID": "00-0037268",
        "JerseyNumber": "27",
        "LastName": "McCollum",
        "FootballName": "Zyon",
        "FirstName": "Zyon",
        "Position": "CB",
        "PositionDescription": "Cornerback",
        "EntryYear": 2022,
        "RookieYear": 2022,
        "Height": "6'04\"",
        "Weight": 200,
        "Birthdate": "1999-05-03T00:00:00",
        "DraftClub": "TB",
        "DraftNumber": 157,
        "Draftround": 5,
        "CurrentClub": "TB",
        "College": "Sam Houston State",
        "CollegeConference": "Southland Conference",
        "StatusDescriptionAbbr": "A01",
        "StatusShortDescription": "Active",
        "Playerid": 54622
    },
    {
        "Season": 2022,
        "SeasonType": "REG",
        "Week": 12,
        "EliasID": "MIL546315",
        "GsisID": "00-0035298",
        "JerseyNumber": "10",
        "LastName": "Miller",
        "FootballName": "Scott",
        "FirstName": "Scott",
        "Position": "WR",
        "PositionDescription": "Wide Receiver",
        "EntryYear": 2019,
        "RookieYear": 2019,
        "Height": "5'11\"",
        "Weight": 174,
        "Birthdate": "1997-07-31T00:00:00",
        "DraftClub": "TB",
        "DraftNumber": 208,
        "Draftround": 6,
        "CurrentClub": "TB",
        "College": "Bowling Green",
        "CollegeConference": "Mid-American Conference",
        "StatusDescriptionAbbr": "A01",
        "StatusShortDescription": "Active",
        "Playerid": 47991
    },
    {
        "Season": 2022,
        "SeasonType": "REG",
        "Week": 12,
        "EliasID": "MOL093253",
        "GsisID": "00-0036048",
        "JerseyNumber": "75",
        "LastName": "Molchon",
        "FootballName": "John",
        "FirstName": "John",
        "Position": "G",
        "PositionDescription": "Guard",
        "EntryYear": 2020,
        "RookieYear": 2020,
        "Height": "6'05\"",
        "Weight": 318,
        "Birthdate": "1997-02-02T00:00:00",
        "DraftClub": null,
        "DraftNumber": null,
        "Draftround": null,
        "CurrentClub": "TB",
        "College": "Boise State",
        "CollegeConference": "Mountain West Conference",
        "StatusDescriptionAbbr": "A01",
        "StatusShortDescription": "Active",
        "Playerid": 52950
    },
    {
        "Season": 2022,
        "SeasonType": "REG",
        "Week": 12,
        "EliasID": "BUN571021",
        "GsisID": "00-0035239",
        "JerseyNumber": "23",
        "LastName": "Murphy-Bunting",
        "FootballName": "Sean",
        "FirstName": "Sean",
        "Position": "CB",
        "PositionDescription": "Cornerback",
        "EntryYear": 2019,
        "RookieYear": 2019,
        "Height": "6'00\"",
        "Weight": 195,
        "Birthdate": "1997-06-19T00:00:00",
        "DraftClub": "TB",
        "DraftNumber": 39,
        "Draftround": 2,
        "CurrentClub": "TB",
        "College": "Central Michigan",
        "CollegeConference": "Mid-American Conference",
        "StatusDescriptionAbbr": "A01",
        "StatusShortDescription": "Active",
        "Playerid": 47822
    },
    {
        "Season": 2022,
        "SeasonType": "REG",
        "Week": 12,
        "EliasID": "NAS727044",
        "GsisID": "00-0033129",
        "JerseyNumber": "94",
        "LastName": "Nassib",
        "FootballName": "Carl",
        "FirstName": "Carl",
        "Position": "OLB",
        "PositionDescription": "Outside Linebacker",
        "EntryYear": 2016,
        "RookieYear": 2016,
        "Height": "6'07\"",
        "Weight": 275,
        "Birthdate": "1993-04-12T00:00:00",
        "DraftClub": "CLV",
        "DraftNumber": 65,
        "Draftround": 3,
        "CurrentClub": "TB",
        "College": "Penn State",
        "CollegeConference": "Big Ten Conference",
        "StatusDescriptionAbbr": "A01",
        "StatusShortDescription": "Active",
        "Playerid": 43354
    },
    {
        "Season": 2022,
        "SeasonType": "REG",
        "Week": 12,
        "EliasID": "NEA222964",
        "GsisID": "00-0032382",
        "JerseyNumber": "22",
        "LastName": "Neal",
        "FootballName": "Keanu",
        "FirstName": "Keanu",
        "Position": "FS",
        "PositionDescription": "Free Safety",
        "EntryYear": 2016,
        "RookieYear": 2016,
        "Height": "6'01\"",
        "Weight": 216,
        "Birthdate": "1995-07-26T00:00:00",
        "DraftClub": "ATL",
        "DraftNumber": 17,
        "Draftround": 1,
        "CurrentClub": "TB",
        "College": "Florida",
        "CollegeConference": "Southeastern Conference",
        "StatusDescriptionAbbr": "A01",
        "StatusShortDescription": "Active",
        "Playerid": 43306
    },
    {
        "Season": 2022,
        "SeasonType": "REG",
        "Week": 12,
        "EliasID": "NEL115040",
        "GsisID": "00-0035254",
        "JerseyNumber": "98",
        "LastName": "Nelson",
        "FootballName": "Anthony",
        "FirstName": "Anthony",
        "Position": "OLB",
        "PositionDescription": "Outside Linebacker",
        "EntryYear": 2019,
        "RookieYear": 2019,
        "Height": "6'07\"",
        "Weight": 272,
        "Birthdate": "1997-03-04T00:00:00",
        "DraftClub": "TB",
        "DraftNumber": 107,
        "Draftround": 4,
        "CurrentClub": "TB",
        "College": "Iowa",
        "CollegeConference": "Big Ten Conference",
        "StatusDescriptionAbbr": "A01",
        "StatusShortDescription": "Active",
        "Playerid": 47890
    },
    {
        "Season": 2022,
        "SeasonType": "REG",
        "Week": 12,
        "EliasID": "NUN250521",
        "GsisID": "00-0031957",
        "JerseyNumber": "56",
        "LastName": "Nunez-Roches",
        "FootballName": "Rakeem",
        "FirstName": "Rakeem",
        "Position": "NT",
        "PositionDescription": "Nose Tackle",
        "EntryYear": 2015,
        "RookieYear": 2015,
        "Height": "6'02\"",
        "Weight": 307,
        "Birthdate": "1993-07-03T00:00:00",
        "DraftClub": "KC",
        "DraftNumber": 217,
        "Draftround": 6,
        "CurrentClub": "TB",
        "College": "Southern Mississippi",
        "CollegeConference": "Conference USA",
        "StatusDescriptionAbbr": "A01",
        "StatusShortDescription": "Active",
        "Playerid": 42560
    },
    {
        "Season": 2022,
        "SeasonType": "REG",
        "Week": 12,
        "EliasID": "OCO519549",
        "GsisID": "00-0033595",
        "JerseyNumber": "79",
        "LastName": "O'Connor",
        "FootballName": "Pat",
        "FirstName": "Patrick",
        "Position": "DE",
        "PositionDescription": "Defensive End",
        "EntryYear": 2017,
        "RookieYear": 2017,
        "Height": "6'04\"",
        "Weight": 270,
        "Birthdate": "1993-11-01T00:00:00",
        "DraftClub": "DET",
        "DraftNumber": 250,
        "Draftround": 7,
        "CurrentClub": "TB",
        "College": "Eastern Michigan",
        "CollegeConference": "Mid-American Conference",
        "StatusDescriptionAbbr": "A01",
        "StatusShortDescription": "Active",
        "Playerid": 45063
    },
    {
        "Season": 2022,
        "SeasonType": "REG",
        "Week": 12,
        "EliasID": "OTT712400",
        "GsisID": "00-0038129",
        "JerseyNumber": "88",
        "LastName": "Otton",
        "FootballName": "Cade",
        "FirstName": "Cade",
        "Position": "TE",
        "PositionDescription": "Tight End",
        "EntryYear": 2022,
        "RookieYear": 2022,
        "Height": "6'05\"",
        "Weight": 250,
        "Birthdate": "1999-04-15T00:00:00",
        "DraftClub": "TB",
        "DraftNumber": 106,
        "Draftround": 4,
        "CurrentClub": "TB",
        "College": "Washington",
        "CollegeConference": "Pacific Twelve Conference",
        "StatusDescriptionAbbr": "A01",
        "StatusShortDescription": "Active",
        "Playerid": 54571
    },
    {
        "Season": 2022,
        "SeasonType": "REG",
        "Week": 12,
        "EliasID": "PER440170",
        "GsisID": "00-0032054",
        "JerseyNumber": "16",
        "LastName": "Perriman",
        "FootballName": "Breshad",
        "FirstName": "Breshad",
        "Position": "WR",
        "PositionDescription": "Wide Receiver",
        "EntryYear": 2015,
        "RookieYear": 2015,
        "Height": "6'02\"",
        "Weight": 215,
        "Birthdate": "1993-09-10T00:00:00",
        "DraftClub": "BLT",
        "DraftNumber": 26,
        "Draftround": 1,
        "CurrentClub": "TB",
        "College": "Central Florida",
        "CollegeConference": "American Athletic Conference",
        "StatusDescriptionAbbr": "A01",
        "StatusShortDescription": "Active",
        "Playerid": 42369
    },
    {
        "Season": 2022,
        "SeasonType": "REG",
        "Week": 12,
        "EliasID": "RUD559717",
        "GsisID": "00-0027981",
        "JerseyNumber": "8",
        "LastName": "Rudolph",
        "FootballName": "Kyle",
        "FirstName": "Kyle",
        "Position": "TE",
        "PositionDescription": "Tight End",
        "EntryYear": 2011,
        "RookieYear": 2011,
        "Height": "6'06\"",
        "Weight": 265,
        "Birthdate": "1989-11-09T00:00:00",
        "DraftClub": "MIN",
        "DraftNumber": 43,
        "Draftround": 2,
        "CurrentClub": "TB",
        "College": "Notre Dame",
        "CollegeConference": "Independent",
        "StatusDescriptionAbbr": "I01",
        "StatusShortDescription": "Inactive",
        "Playerid": 37118
    },
    {
        "Season": 2022,
        "SeasonType": "REG",
        "Week": 12,
        "EliasID": "SEN026161",
        "GsisID": "00-0034363",
        "JerseyNumber": "95",
        "LastName": "Senat",
        "FootballName": "Deadrin",
        "FirstName": "Deadrin",
        "Position": "DT",
        "PositionDescription": "Defensive Tackle",
        "EntryYear": 2018,
        "RookieYear": 2018,
        "Height": "6'01\"",
        "Weight": 305,
        "Birthdate": "1994-07-22T00:00:00",
        "DraftClub": "ATL",
        "DraftNumber": 90,
        "Draftround": 3,
        "CurrentClub": "TB",
        "College": "South Florida",
        "CollegeConference": "American Athletic Conference",
        "StatusDescriptionAbbr": "A01",
        "StatusShortDescription": "Active",
        "Playerid": 46159
    },
    {
        "Season": 2022,
        "SeasonType": "REG",
        "Week": 12,
        "EliasID": "SMI221725",
        "GsisID": "00-0032217",
        "JerseyNumber": "76",
        "LastName": "Smith",
        "FootballName": "Donovan",
        "FirstName": "Donovan",
        "Position": "T",
        "PositionDescription": "Tackle",
        "EntryYear": 2015,
        "RookieYear": 2015,
        "Height": "6'06\"",
        "Weight": 338,
        "Birthdate": "1993-06-23T00:00:00",
        "DraftClub": "TB",
        "DraftNumber": 34,
        "Draftround": 2,
        "CurrentClub": "TB",
        "College": "Penn State",
        "CollegeConference": "Big Ten Conference",
        "StatusDescriptionAbbr": "A01",
        "StatusShortDescription": "Active",
        "Playerid": 42377
    },
    {
        "Season": 2022,
        "SeasonType": "REG",
        "Week": 12,
        "EliasID": "SUC073828",
        "GsisID": "00-0026968",
        "JerseyNumber": "3",
        "LastName": "Succop",
        "FootballName": "Ryan",
        "FirstName": "Ryan",
        "Position": "K",
        "PositionDescription": "Kicker",
        "EntryYear": 2009,
        "RookieYear": 2009,
        "Height": "6'02\"",
        "Weight": 218,
        "Birthdate": "1986-09-19T00:00:00",
        "DraftClub": "KC",
        "DraftNumber": 256,
        "Draftround": 7,
        "CurrentClub": "TB",
        "College": "South Carolina",
        "CollegeConference": "Southeastern Conference",
        "StatusDescriptionAbbr": "A01",
        "StatusShortDescription": "Active",
        "Playerid": 34707
    },
    {
        "Season": 2022,
        "SeasonType": "REG",
        "Week": 12,
        "EliasID": "TRA389332",
        "GsisID": "00-0036928",
        "JerseyNumber": "2",
        "LastName": "Trask",
        "FootballName": "Kyle",
        "FirstName": "Kyle",
        "Position": "QB",
        "PositionDescription": "Quarterback",
        "EntryYear": 2021,
        "RookieYear": 2021,
        "Height": "6'05\"",
        "Weight": 240,
        "Birthdate": "1998-03-06T00:00:00",
        "DraftClub": "TB",
        "DraftNumber": 64,
        "Draftround": 2,
        "CurrentClub": "TB",
        "College": "Florida",
        "CollegeConference": "Southeastern Conference",
        "StatusDescriptionAbbr": "I01",
        "StatusShortDescription": "Inactive",
        "Playerid": 53493
    },
    {
        "Season": 2022,
        "SeasonType": "REG",
        "Week": 12,
        "EliasID": "TRI258690",
        "GsisID": "00-0033196",
        "JerseyNumber": "97",
        "LastName": "Triner",
        "FootballName": "Zach",
        "FirstName": "Zach",
        "Position": "LS",
        "PositionDescription": "Long Snapper",
        "EntryYear": 2016,
        "RookieYear": 2017,
        "Height": "6'02\"",
        "Weight": 245,
        "Birthdate": "1991-01-30T00:00:00",
        "DraftClub": null,
        "DraftNumber": null,
        "Draftround": null,
        "CurrentClub": "TB",
        "College": "Assumption",
        "CollegeConference": "Northeast-10 Conference",
        "StatusDescriptionAbbr": "A01",
        "StatusShortDescription": "Active",
        "Playerid": 44376
    },
    {
        "Season": 2022,
        "SeasonType": "REG",
        "Week": 12,
        "EliasID": "TRY409291",
        "GsisID": "00-0036967",
        "JerseyNumber": "9",
        "LastName": "Tryon",
        "FootballName": "Joe",
        "FirstName": "Joseph",
        "Position": "OLB",
        "PositionDescription": "Outside Linebacker",
        "EntryYear": 2021,
        "RookieYear": 2021,
        "Height": "6'05\"",
        "Weight": 262,
        "Birthdate": "1999-04-30T00:00:00",
        "DraftClub": "TB",
        "DraftNumber": 32,
        "Draftround": 1,
        "CurrentClub": "TB",
        "College": "Washington",
        "CollegeConference": "Pacific Twelve Conference",
        "StatusDescriptionAbbr": "A01",
        "StatusShortDescription": "Active",
        "Playerid": 53461
    },
    {
        "Season": 2022,
        "SeasonType": "REG",
        "Week": 12,
        "EliasID": "TUR626317",
        "GsisID": "00-0037488",
        "JerseyNumber": "34",
        "LastName": "Turner",
        "FootballName": "Nolan",
        "FirstName": "Nolan",
        "Position": "DB",
        "PositionDescription": "Defensive Back",
        "EntryYear": 2022,
        "RookieYear": 2022,
        "Height": "6'00\"",
        "Weight": 200,
        "Birthdate": "1997-11-29T00:00:00",
        "DraftClub": null,
        "DraftNumber": null,
        "Draftround": null,
        "CurrentClub": "TB",
        "College": "Clemson",
        "CollegeConference": "Atlantic Coast Conference",
        "StatusDescriptionAbbr": "I01",
        "StatusShortDescription": "Inactive",
        "Playerid": 55076
    },
    {
        "Season": 2022,
        "SeasonType": "REG",
        "Week": 12,
        "EliasID": "VAU458202",
        "GsisID": "00-0036450",
        "JerseyNumber": "21",
        "LastName": "Vaughn",
        "FootballName": "Ke'Shawn",
        "FirstName": "Ke'Shawn",
        "Position": "RB",
        "PositionDescription": "Running Back",
        "EntryYear": 2020,
        "RookieYear": 2020,
        "Height": "5'10\"",
        "Weight": 215,
        "Birthdate": "1997-05-04T00:00:00",
        "DraftClub": "TB",
        "DraftNumber": 76,
        "Draftround": 3,
        "CurrentClub": "TB",
        "College": "Vanderbilt",
        "CollegeConference": "Southeastern Conference",
        "StatusDescriptionAbbr": "A01",
        "StatusShortDescription": "Active",
        "Playerid": 52484
    },
    {
        "Season": 2022,
        "SeasonType": "REG",
        "Week": 12,
        "EliasID": "VEA065410",
        "GsisID": "00-0034773",
        "JerseyNumber": "50",
        "LastName": "Vea",
        "FootballName": "Vita",
        "FirstName": "Tevita",
        "Position": "NT",
        "PositionDescription": "Nose Tackle",
        "EntryYear": 2018,
        "RookieYear": 2018,
        "Height": "6'04\"",
        "Weight": 347,
        "Birthdate": "1995-02-05T00:00:00",
        "DraftClub": "TB",
        "DraftNumber": 12,
        "Draftround": 1,
        "CurrentClub": "TB",
        "College": "Washington",
        "CollegeConference": "Pacific Twelve Conference",
        "StatusDescriptionAbbr": "A01",
        "StatusShortDescription": "Active",
        "Playerid": 46081
    },
    {
        "Season": 2022,
        "SeasonType": "REG",
        "Week": 12,
        "EliasID": "WAL756673",
        "GsisID": "00-0036123",
        "JerseyNumber": "73",
        "LastName": "Walton",
        "FootballName": "Brandon",
        "FirstName": "Brandon",
        "Position": "G",
        "PositionDescription": "Guard",
        "EntryYear": 2020,
        "RookieYear": 2020,
        "Height": "6'05\"",
        "Weight": 300,
        "Birthdate": "1998-03-18T00:00:00",
        "DraftClub": null,
        "DraftNumber": null,
        "Draftround": null,
        "CurrentClub": "TB",
        "College": "Florida Atlantic",
        "CollegeConference": "Conference USA",
        "StatusDescriptionAbbr": "A01",
        "StatusShortDescription": "Active",
        "Playerid": 53027
    },
    {
        "Season": 2022,
        "SeasonType": "REG",
        "Week": 12,
        "EliasID": "WEL457772",
        "GsisID": "00-0030829",
        "JerseyNumber": "72",
        "LastName": "Wells",
        "FootballName": "Josh",
        "FirstName": "Joshua",
        "Position": "T",
        "PositionDescription": "Tackle",
        "EntryYear": 2014,
        "RookieYear": 2014,
        "Height": "6'06\"",
        "Weight": 306,
        "Birthdate": "1991-02-14T00:00:00",
        "DraftClub": null,
        "DraftNumber": null,
        "Draftround": null,
        "CurrentClub": "TB",
        "College": "James Madison",
        "CollegeConference": "Colonial Athletic Association",
        "StatusDescriptionAbbr": "A01",
        "StatusShortDescription": "Active",
        "Playerid": 41667
    },
    {
        "Season": 2022,
        "SeasonType": "REG",
        "Week": 12,
        "EliasID": "WHI393110",
        "GsisID": "00-0037256",
        "JerseyNumber": "29",
        "LastName": "White",
        "FootballName": "Rachaad",
        "FirstName": "Rachaad",
        "Position": "RB",
        "PositionDescription": "Running Back",
        "EntryYear": 2022,
        "RookieYear": 2022,
        "Height": "6'02\"",
        "Weight": 210,
        "Birthdate": "1999-01-21T00:00:00",
        "DraftClub": "TB",
        "DraftNumber": 91,
        "Draftround": 3,
        "CurrentClub": "TB",
        "College": "Arizona State",
        "CollegeConference": "Pacific Twelve Conference",
        "StatusDescriptionAbbr": "A01",
        "StatusShortDescription": "Active",
        "Playerid": 54556
    },
    {
        "Season": 2022,
        "SeasonType": "REG",
        "Week": 12,
        "EliasID": "WHI399982",
        "GsisID": "00-0035707",
        "JerseyNumber": "45",
        "LastName": "White",
        "FootballName": "Devin",
        "FirstName": "Devin",
        "Position": "ILB",
        "PositionDescription": "Inside Linebacker",
        "EntryYear": 2019,
        "RookieYear": 2019,
        "Height": "6'00\"",
        "Weight": 237,
        "Birthdate": "1998-02-17T00:00:00",
        "DraftClub": "TB",
        "DraftNumber": 5,
        "Draftround": 1,
        "CurrentClub": "TB",
        "College": "Louisiana State",
        "CollegeConference": "Southeastern Conference",
        "StatusDescriptionAbbr": "A01",
        "StatusShortDescription": "Active",
        "Playerid": 47788
    },
    {
        "Season": 2022,
        "SeasonType": "REG",
        "Week": 12,
        "EliasID": "WIN159348",
        "GsisID": "00-0036411",
        "JerseyNumber": "31",
        "LastName": "Winfield",
        "FootballName": "Antoine",
        "FirstName": "Antoine",
        "Position": "FS",
        "PositionDescription": "Free Safety",
        "EntryYear": 2020,
        "RookieYear": 2020,
        "Height": "5'09\"",
        "Weight": 205,
        "Birthdate": "1998-08-16T00:00:00",
        "DraftClub": "TB",
        "DraftNumber": 45,
        "Draftround": 2,
        "CurrentClub": "TB",
        "College": "Minnesota",
        "CollegeConference": "Big Ten Conference",
        "StatusDescriptionAbbr": "A01",
        "StatusShortDescription": "Active",
        "Playerid": 52453
    },
    {
        "Season": 2022,
        "SeasonType": "REG",
        "Week": 12,
        "EliasID": "WIR370129",
        "GsisID": "00-0036406",
        "JerseyNumber": "78",
        "LastName": "Wirfs",
        "FootballName": "Tristan",
        "FirstName": "Tristan",
        "Position": "T",
        "PositionDescription": "Tackle",
        "EntryYear": 2020,
        "RookieYear": 2020,
        "Height": "6'05\"",
        "Weight": 322,
        "Birthdate": "1999-01-24T00:00:00",
        "DraftClub": "TB",
        "DraftNumber": 13,
        "Draftround": 1,
        "CurrentClub": "TB",
        "College": "Iowa",
        "CollegeConference": "Big Ten Conference",
        "StatusDescriptionAbbr": "A01",
        "StatusShortDescription": "Active",
        "Playerid": 52421
    }
]